<?xml version="1.0" encoding="iso-8859-1" ?>

<CustomData>
  <CustomGroups>
    <CustomGroup>
      <name>Foreign_Donor</name>
      <title>Foreign Donor</title>
      <extends>Contribution</extends>
      <style>Inline</style>
      <collapse_display>1</collapse_display>
      <help_pre></help_pre>
      <help_post></help_post>
      <weight>3</weight>
      <is_active>1</is_active>
      <table_name>civicrm_value_foreign_donor_5</table_name>
      <is_multiple>0</is_multiple>
      <collapse_adv_display>0</collapse_adv_display>
      <created_date>2019-01-20 22:24:21</created_date>
      <is_reserved>0</is_reserved>
      <is_public>1</is_public>
    </CustomGroup>
  </CustomGroups>
  <CustomFields>
    <CustomField>
      <name>Foreign_Donor_declaration_recorded</name>
      <label>Foreign Donor declaration recorded</label>
      <data_type>Boolean</data_type>
      <html_type>Radio</html_type>
      <is_searchable>1</is_searchable>
      <is_search_range>0</is_search_range>
      <weight>1</weight>
      <help_pre>Was this contribution made by an individual affirming they are not a foreign donor?</help_pre>
      <help_post>The definition of a Foreign Donor is found under section 287AA of the Commonwealth Electoral Act 1918.</help_post>
      <is_active>1</is_active>
      <text_length>255</text_length>
      <note_columns>60</note_columns>
      <note_rows>4</note_rows>
      <column_name>foreign_donor_declaration_record_15</column_name>
      <in_selector>0</in_selector>
      <custom_group_name>Foreign_Donor</custom_group_name>
    </CustomField>
  </CustomFields>
</CustomData>
